uniparser_albanian/__init__.py
uniparser_albanian/data_nodiacritics/__init__.py
uniparser_albanian/data_nodiacritics/albanian_disambiguation.cg3
uniparser_albanian/data_nodiacritics/bad_analyses.txt
uniparser_albanian/data_nodiacritics/derivations.txt
uniparser_albanian/data_nodiacritics/lexemes.txt
uniparser_albanian/data_nodiacritics/paradigms.txt
uniparser_albanian/data_strict/__init__.py
uniparser_albanian/data_strict/albanian_disambiguation.cg3
uniparser_albanian/data_strict/bad_analyses.txt
uniparser_albanian/data_strict/derivations.txt
uniparser_albanian/data_strict/lexemes.txt
uniparser_albanian/data_strict/paradigms.txt
uniparser_albanian-2.3.0.dist-info/LICENSE
uniparser_albanian-2.3.0.dist-info/METADATA
uniparser_albanian-2.3.0.dist-info/WHEEL
uniparser_albanian-2.3.0.dist-info/top_level.txt
uniparser_albanian-2.3.0.dist-info/RECORD
